README.md
fanout.py
setup.cfg
setup.py
fanout.egg-info/PKG-INFO
fanout.egg-info/SOURCES.txt
fanout.egg-info/dependency_links.txt
fanout.egg-info/requires.txt
fanout.egg-info/top_level.txt