Metadata-Version: 1.1
Name: fanout
Version: 1.3.0
Summary: Fanout.io library
Home-page: https://github.com/fanout/pyfanout
Author: Justin Karneges
Author-email: justin@fanout.io
License: MIT
Platform: UNKNOWN
Classifier: Topic :: Utilities
Classifier: License :: OSI Approved :: MIT License
